IdealFlow/Classifier.py
IdealFlow/Command.py
IdealFlow/Network.py
IdealFlow/Table.py
IdealFlow/Text.py
IdealFlow/__init__.py
IdealFlowNetwork-1.15.5.dist-info/METADATA
IdealFlowNetwork-1.15.5.dist-info/WHEEL
IdealFlowNetwork-1.15.5.dist-info/top_level.txt
IdealFlowNetwork-1.15.5.dist-info/RECORD
